{
    "name": "apa6-tcs",
    "plugins": [
        "ptmp-tcs"
    ],
    "proxies": [
        {
            "data": {
                "detid": -1,
                "input": {
                    "socket": {
                        "connect": [
                            "tcp://10.73.136.60:15151"
                        ],
                        "hwm": 10000,
                        "type": "SUB"
                    }
                },
                "name": "tp-window-apa6-link00",
                "output": {
                    "socket": {
                        "bind": [
                            "inproc://tc-window-zipper-apa6-link00"
                        ],
                        "hwm": 1000,
                        "type": "PUSH"
                    }
                },
                "sync_time": 10,
                "tardy_policy": "drop",
                "tbuf": 250000,
                "toffset": 0,
                "tspan": 2500
            },
            "name": "tc-window-apa6-link00",
            "type": "window"
        },
        {
            "data": {
                "detid": -1,
                "input": {
                    "socket": {
                        "connect": [
                            "tcp://10.73.136.60:15152"
                        ],
                        "hwm": 10000,
                        "type": "SUB"
                    }
                },
                "name": "tp-window-apa6-link01",
                "output": {
                    "socket": {
                        "bind": [
                            "inproc://tc-window-zipper-apa6-link01"
                        ],
                        "hwm": 1000,
                        "type": "PUSH"
                    }
                },
                "sync_time": 10,
                "tardy_policy": "drop",
                "tbuf": 250000,
                "toffset": 0,
                "tspan": 2500
            },
            "name": "tc-window-apa6-link01",
            "type": "window"
        },
        {
            "data": {
                "detid": -1,
                "input": {
                    "socket": {
                        "connect": [
                            "tcp://10.73.136.60:15153"
                        ],
                        "hwm": 10000,
                        "type": "SUB"
                    }
                },
                "name": "tp-window-apa6-link02",
                "output": {
                    "socket": {
                        "bind": [
                            "inproc://tc-window-zipper-apa6-link02"
                        ],
                        "hwm": 1000,
                        "type": "PUSH"
                    }
                },
                "sync_time": 10,
                "tardy_policy": "drop",
                "tbuf": 250000,
                "toffset": 0,
                "tspan": 2500
            },
            "name": "tc-window-apa6-link02",
            "type": "window"
        },
        {
            "data": {
                "detid": -1,
                "input": {
                    "socket": {
                        "connect": [
                            "tcp://10.73.136.60:15154"
                        ],
                        "hwm": 10000,
                        "type": "SUB"
                    }
                },
                "name": "tp-window-apa6-link03",
                "output": {
                    "socket": {
                        "bind": [
                            "inproc://tc-window-zipper-apa6-link03"
                        ],
                        "hwm": 1000,
                        "type": "PUSH"
                    }
                },
                "sync_time": 10,
                "tardy_policy": "drop",
                "tbuf": 250000,
                "toffset": 0,
                "tspan": 2500
            },
            "name": "tc-window-apa6-link03",
            "type": "window"
        },
        {
            "data": {
                "detid": -1,
                "input": {
                    "socket": {
                        "connect": [
                            "tcp://10.73.136.60:15155"
                        ],
                        "hwm": 10000,
                        "type": "SUB"
                    }
                },
                "name": "tp-window-apa6-link04",
                "output": {
                    "socket": {
                        "bind": [
                            "inproc://tc-window-zipper-apa6-link04"
                        ],
                        "hwm": 1000,
                        "type": "PUSH"
                    }
                },
                "sync_time": 10,
                "tardy_policy": "drop",
                "tbuf": 250000,
                "toffset": 0,
                "tspan": 2500
            },
            "name": "tc-window-apa6-link04",
            "type": "window"
        },
        {
            "data": {
                "detid": -1,
                "input": {
                    "socket": {
                        "connect": [
                            "tcp://10.73.136.60:15156"
                        ],
                        "hwm": 10000,
                        "type": "SUB"
                    }
                },
                "name": "tp-window-apa6-link05",
                "output": {
                    "socket": {
                        "bind": [
                            "inproc://tc-window-zipper-apa6-link05"
                        ],
                        "hwm": 1000,
                        "type": "PUSH"
                    }
                },
                "sync_time": 10,
                "tardy_policy": "drop",
                "tbuf": 250000,
                "toffset": 0,
                "tspan": 2500
            },
            "name": "tc-window-apa6-link05",
            "type": "window"
        },
        {
            "data": {
                "detid": -1,
                "input": {
                    "socket": {
                        "connect": [
                            "tcp://10.73.136.60:15157"
                        ],
                        "hwm": 10000,
                        "type": "SUB"
                    }
                },
                "name": "tp-window-apa6-link06",
                "output": {
                    "socket": {
                        "bind": [
                            "inproc://tc-window-zipper-apa6-link06"
                        ],
                        "hwm": 1000,
                        "type": "PUSH"
                    }
                },
                "sync_time": 10,
                "tardy_policy": "drop",
                "tbuf": 250000,
                "toffset": 0,
                "tspan": 2500
            },
            "name": "tc-window-apa6-link06",
            "type": "window"
        },
        {
            "data": {
                "detid": -1,
                "input": {
                    "socket": {
                        "connect": [
                            "tcp://10.73.136.60:15158"
                        ],
                        "hwm": 10000,
                        "type": "SUB"
                    }
                },
                "name": "tp-window-apa6-link07",
                "output": {
                    "socket": {
                        "bind": [
                            "inproc://tc-window-zipper-apa6-link07"
                        ],
                        "hwm": 1000,
                        "type": "PUSH"
                    }
                },
                "sync_time": 10,
                "tardy_policy": "drop",
                "tbuf": 250000,
                "toffset": 0,
                "tspan": 2500
            },
            "name": "tc-window-apa6-link07",
            "type": "window"
        },
        {
            "data": {
                "detid": -1,
                "input": {
                    "socket": {
                        "connect": [
                            "tcp://10.73.136.60:15159"
                        ],
                        "hwm": 10000,
                        "type": "SUB"
                    }
                },
                "name": "tp-window-apa6-link08",
                "output": {
                    "socket": {
                        "bind": [
                            "inproc://tc-window-zipper-apa6-link08"
                        ],
                        "hwm": 1000,
                        "type": "PUSH"
                    }
                },
                "sync_time": 10,
                "tardy_policy": "drop",
                "tbuf": 250000,
                "toffset": 0,
                "tspan": 2500
            },
            "name": "tc-window-apa6-link08",
            "type": "window"
        },
        {
            "data": {
                "detid": -1,
                "input": {
                    "socket": {
                        "connect": [
                            "tcp://10.73.136.60:15160"
                        ],
                        "hwm": 10000,
                        "type": "SUB"
                    }
                },
                "name": "tp-window-apa6-link09",
                "output": {
                    "socket": {
                        "bind": [
                            "inproc://tc-window-zipper-apa6-link09"
                        ],
                        "hwm": 1000,
                        "type": "PUSH"
                    }
                },
                "sync_time": 10,
                "tardy_policy": "drop",
                "tbuf": 250000,
                "toffset": 0,
                "tspan": 2500
            },
            "name": "tc-window-apa6-link09",
            "type": "window"
        },
        {
            "data": {
                "detid": -1,
                "input": {
                    "socket": {
                        "connect": [
                            "inproc://tc-window-zipper-apa6-link00",
                            "inproc://tc-window-zipper-apa6-link01",
                            "inproc://tc-window-zipper-apa6-link02",
                            "inproc://tc-window-zipper-apa6-link03",
                            "inproc://tc-window-zipper-apa6-link04",
                            "inproc://tc-window-zipper-apa6-link05",
                            "inproc://tc-window-zipper-apa6-link06",
                            "inproc://tc-window-zipper-apa6-link07",
                            "inproc://tc-window-zipper-apa6-link08",
                            "inproc://tc-window-zipper-apa6-link09"
                        ],
                        "hwm": 1000,
                        "type": "PULL"
                    }
                },
                "name": "apa6-zipper",
                "output": {
                    "socket": {
                        "bind": [
                            "inproc://tc-zipper-tcfinder-apa6"
                        ],
                        "hwm": 1000,
                        "type": "PUSH"
                    }
                },
                "sync_time": 10,
                "tardy_policy": "drop",
                "tbuf": 250000,
                "toffset": 0,
                "tspan": 2500
            },
            "name": "tc-zipper-apa6",
            "type": "zipper"
        },
        {
            "data": {
                "input": {
                    "socket": {
                        "connect": [
                            "inproc://tc-zipper-tcfinder-apa6"
                        ],
                        "hwm": 1000,
                        "type": "PULL"
                    }
                },
                "method": "pdune-adjacency-tc",
                "name": "apa6-adj-tcs",
                "output": {
                    "socket": {
                        "bind": [
                            "tcp://10.73.136.32:40502"
                        ],
                        "hwm": 10000,
                        "type": "PUB"
                    }
                }
            },
            "name": "tc-finder-apa6",
            "type": "filter"
        }
    ]
}